kanren/__init__.py
kanren/arith.py
kanren/assoccomm.py
kanren/cons.py
kanren/core.py
kanren/dispatch.py
kanren/facts.py
kanren/goals.py
kanren/term.py
kanren/util.py
kanren-0.3.0.dist-info/licenses/LICENSE.txt
kanren-0.3.0.dist-info/METADATA
kanren-0.3.0.dist-info/WHEEL
kanren-0.3.0.dist-info/top_level.txt
kanren-0.3.0.dist-info/RECORD
