Metadata-Version: 2.4
Name: kanren
Version: 0.3.0
Summary: Logic Programming in python
Home-page: http://github.com/logpy/logpy
Author: Matthew Rocklin
Author-email: mrocklin@gmail.com
License: BSD
Classifier: Development Status :: 5 - Production/Stable
Classifier: License :: OSI Approved :: BSD License
Classifier: Programming Language :: Python
Classifier: Programming Language :: Python :: 3
Classifier: Programming Language :: Python :: Implementation :: CPython
Classifier: Programming Language :: Python :: Implementation :: PyPy
License-File: LICENSE.txt
Requires-Dist: toolz
Requires-Dist: multipledispatch
Requires-Dist: unification>=0.3.1
Dynamic: author
Dynamic: author-email
Dynamic: classifier
Dynamic: description
Dynamic: description-content-type
Dynamic: home-page
Dynamic: license
Dynamic: license-file
Dynamic: requires-dist
Dynamic: summary
